ltsv2json/__init__.py
ltsv2json-1.0.2.dist-info/LICENSE
ltsv2json-1.0.2.dist-info/METADATA
ltsv2json-1.0.2.dist-info/WHEEL
ltsv2json-1.0.2.dist-info/entry_points.txt
ltsv2json-1.0.2.dist-info/top_level.txt
ltsv2json-1.0.2.dist-info/RECORD
